{
	"resources": [
		{
			"resource": {
				"format": "text/plain",
				"language": "de",
				"@type": "cnt:ContentAsText",
				"chars": "145 [von fremder Hand]"
			},
			"@context": "https://iiif.io/api/presentation/2/context.json",
			"motivation": "sc:painting",
			"@type": "oa:Annotation",
			"@id": "https://kraus1933.acdh.oeaw.ac.at/iiif_manifests/HIN-176044/HIN-176044_0289/transkript.json#line_1561558244946_671",
			"on": "https://kraus1933.acdh.oeaw.ac.at/iiif_manifests/HIN-176044/HIN-176044_0289#xywh=849,97,150,94"
		},
		{
			"resource": {
				"format": "text/plain",
				"language": "de",
				"@type": "cnt:ContentAsText",
				"chars": "[?]"
			},
			"@context": "https://iiif.io/api/presentation/2/context.json",
			"motivation": "sc:painting",
			"@type": "oa:Annotation",
			"@id": "https://kraus1933.acdh.oeaw.ac.at/iiif_manifests/HIN-176044/HIN-176044_0289/transkript.json#line_1561558256449_674",
			"on": "https://kraus1933.acdh.oeaw.ac.at/iiif_manifests/HIN-176044/HIN-176044_0289#xywh=423,94,94,53"
		},
		{
			"resource": {
				"format": "text/plain",
				"language": "de",
				"@type": "cnt:ContentAsText",
				"chars": "[??]"
			},
			"@context": "https://iiif.io/api/presentation/2/context.json",
			"motivation": "sc:painting",
			"@type": "oa:Annotation",
			"@id": "https://kraus1933.acdh.oeaw.ac.at/iiif_manifests/HIN-176044/HIN-176044_0289/transkript.json#line_1561558263300_677",
			"on": "https://kraus1933.acdh.oeaw.ac.at/iiif_manifests/HIN-176044/HIN-176044_0289#xywh=327,84,479,119"
		},
		{
			"resource": {
				"format": "text/plain",
				"language": "de",
				"@type": "cnt:ContentAsText",
				"chars": "[??]"
			},
			"@context": "https://iiif.io/api/presentation/2/context.json",
			"motivation": "sc:painting",
			"@type": "oa:Annotation",
			"@id": "https://kraus1933.acdh.oeaw.ac.at/iiif_manifests/HIN-176044/HIN-176044_0289/transkript.json#line_1561558267080_680",
			"on": "https://kraus1933.acdh.oeaw.ac.at/iiif_manifests/HIN-176044/HIN-176044_0289#xywh=476,177,339,82"
		},
		{
			"resource": {
				"format": "text/plain",
				"language": "de",
				"@type": "cnt:ContentAsText",
				"chars": "Zuversichtlich[?]"
			},
			"@context": "https://iiif.io/api/presentation/2/context.json",
			"motivation": "sc:painting",
			"@type": "oa:Annotation",
			"@id": "https://kraus1933.acdh.oeaw.ac.at/iiif_manifests/HIN-176044/HIN-176044_0289/transkript.json#line_1561558271932_683",
			"on": "https://kraus1933.acdh.oeaw.ac.at/iiif_manifests/HIN-176044/HIN-176044_0289#xywh=166,277,385,151"
		},
		{
			"resource": {
				"format": "text/plain",
				"language": "de",
				"@type": "cnt:ContentAsText",
				"chars": "[?], die"
			},
			"@context": "https://iiif.io/api/presentation/2/context.json",
			"motivation": "sc:painting",
			"@type": "oa:Annotation",
			"@id": "https://kraus1933.acdh.oeaw.ac.at/iiif_manifests/HIN-176044/HIN-176044_0289/transkript.json#line_1561558278738_686",
			"on": "https://kraus1933.acdh.oeaw.ac.at/iiif_manifests/HIN-176044/HIN-176044_0289#xywh=220,398,453,121"
		},
		{
			"resource": {
				"format": "text/plain",
				"language": "de",
				"@type": "cnt:ContentAsText",
				"chars": "jenem deutschen Geiste"
			},
			"@context": "https://iiif.io/api/presentation/2/context.json",
			"motivation": "sc:painting",
			"@type": "oa:Annotation",
			"@id": "https://kraus1933.acdh.oeaw.ac.at/iiif_manifests/HIN-176044/HIN-176044_0289/transkript.json#line_1561558287263_689",
			"on": "https://kraus1933.acdh.oeaw.ac.at/iiif_manifests/HIN-176044/HIN-176044_0289#xywh=196,484,420,115"
		},
		{
			"resource": {
				"format": "text/plain",
				"language": "de",
				"@type": "cnt:ContentAsText",
				"chars": "der noch den Reichstagsbrand als"
			},
			"@context": "https://iiif.io/api/presentation/2/context.json",
			"motivation": "sc:painting",
			"@type": "oa:Annotation",
			"@id": "https://kraus1933.acdh.oeaw.ac.at/iiif_manifests/HIN-176044/HIN-176044_0289/transkript.json#line_1561558299437_692",
			"on": "https://kraus1933.acdh.oeaw.ac.at/iiif_manifests/HIN-176044/HIN-176044_0289#xywh=159,570,544,121"
		},
		{
			"resource": {
				"format": "text/plain",
				"language": "de",
				"@type": "cnt:ContentAsText",
				"chars": "[??]"
			},
			"@context": "https://iiif.io/api/presentation/2/context.json",
			"motivation": "sc:painting",
			"@type": "oa:Annotation",
			"@id": "https://kraus1933.acdh.oeaw.ac.at/iiif_manifests/HIN-176044/HIN-176044_0289/transkript.json#line_1561558308446_695",
			"on": "https://kraus1933.acdh.oeaw.ac.at/iiif_manifests/HIN-176044/HIN-176044_0289#xywh=187,660,437,111"
		},
		{
			"resource": {
				"format": "text/plain",
				"language": "de",
				"@type": "cnt:ContentAsText",
				"chars": "[?]"
			},
			"@context": "https://iiif.io/api/presentation/2/context.json",
			"motivation": "sc:painting",
			"@type": "oa:Annotation",
			"@id": "https://kraus1933.acdh.oeaw.ac.at/iiif_manifests/HIN-176044/HIN-176044_0289/transkript.json#line_1561558347174_699",
			"on": "https://kraus1933.acdh.oeaw.ac.at/iiif_manifests/HIN-176044/HIN-176044_0289#xywh=222,736,216,91"
		},
		{
			"resource": {
				"format": "text/plain",
				"language": "de",
				"@type": "cnt:ContentAsText",
				"chars": "Partei[?] Sorge tr\u00fcgen"
			},
			"@context": "https://iiif.io/api/presentation/2/context.json",
			"motivation": "sc:painting",
			"@type": "oa:Annotation",
			"@id": "https://kraus1933.acdh.oeaw.ac.at/iiif_manifests/HIN-176044/HIN-176044_0289/transkript.json#line_1561558358032_702",
			"on": "https://kraus1933.acdh.oeaw.ac.at/iiif_manifests/HIN-176044/HIN-176044_0289#xywh=193,757,580,162"
		},
		{
			"resource": {
				"format": "text/plain",
				"language": "de",
				"@type": "cnt:ContentAsText",
				"chars": "[??]"
			},
			"@context": "https://iiif.io/api/presentation/2/context.json",
			"motivation": "sc:painting",
			"@type": "oa:Annotation",
			"@id": "https://kraus1933.acdh.oeaw.ac.at/iiif_manifests/HIN-176044/HIN-176044_0289/transkript.json#line_1561558365104_705",
			"on": "https://kraus1933.acdh.oeaw.ac.at/iiif_manifests/HIN-176044/HIN-176044_0289#xywh=209,865,380,112"
		},
		{
			"resource": {
				"format": "text/plain",
				"language": "de",
				"@type": "cnt:ContentAsText",
				"chars": "[?]"
			},
			"@context": "https://iiif.io/api/presentation/2/context.json",
			"motivation": "sc:painting",
			"@type": "oa:Annotation",
			"@id": "https://kraus1933.acdh.oeaw.ac.at/iiif_manifests/HIN-176044/HIN-176044_0289/transkript.json#line_1561558387913_708",
			"on": "https://kraus1933.acdh.oeaw.ac.at/iiif_manifests/HIN-176044/HIN-176044_0289#xywh=250,953,252,90"
		},
		{
			"resource": {
				"format": "text/plain",
				"language": "de",
				"@type": "cnt:ContentAsText",
				"chars": "[??]"
			},
			"@context": "https://iiif.io/api/presentation/2/context.json",
			"motivation": "sc:painting",
			"@type": "oa:Annotation",
			"@id": "https://kraus1933.acdh.oeaw.ac.at/iiif_manifests/HIN-176044/HIN-176044_0289/transkript.json#line_1561558393759_711",
			"on": "https://kraus1933.acdh.oeaw.ac.at/iiif_manifests/HIN-176044/HIN-176044_0289#xywh=156,993,391,146"
		},
		{
			"resource": {
				"format": "text/plain",
				"language": "de",
				"@type": "cnt:ContentAsText",
				"chars": "[??]"
			},
			"@context": "https://iiif.io/api/presentation/2/context.json",
			"motivation": "sc:painting",
			"@type": "oa:Annotation",
			"@id": "https://kraus1933.acdh.oeaw.ac.at/iiif_manifests/HIN-176044/HIN-176044_0289/transkript.json#line_1561558401641_714",
			"on": "https://kraus1933.acdh.oeaw.ac.at/iiif_manifests/HIN-176044/HIN-176044_0289#xywh=187,1074,367,126"
		},
		{
			"resource": {
				"format": "text/plain",
				"language": "de",
				"@type": "cnt:ContentAsText",
				"chars": "[??]"
			},
			"@context": "https://iiif.io/api/presentation/2/context.json",
			"motivation": "sc:painting",
			"@type": "oa:Annotation",
			"@id": "https://kraus1933.acdh.oeaw.ac.at/iiif_manifests/HIN-176044/HIN-176044_0289/transkript.json#line_1561558417593_718",
			"on": "https://kraus1933.acdh.oeaw.ac.at/iiif_manifests/HIN-176044/HIN-176044_0289#xywh=172,1163,370,123"
		},
		{
			"resource": {
				"format": "text/plain",
				"language": "de",
				"@type": "cnt:ContentAsText",
				"chars": "[??]"
			},
			"@context": "https://iiif.io/api/presentation/2/context.json",
			"motivation": "sc:painting",
			"@type": "oa:Annotation",
			"@id": "https://kraus1933.acdh.oeaw.ac.at/iiif_manifests/HIN-176044/HIN-176044_0289/transkript.json#line_1561558425979_721",
			"on": "https://kraus1933.acdh.oeaw.ac.at/iiif_manifests/HIN-176044/HIN-176044_0289#xywh=203,1260,318,113"
		},
		{
			"resource": {
				"format": "text/plain",
				"language": "de",
				"@type": "cnt:ContentAsText",
				"chars": "[??]"
			},
			"@context": "https://iiif.io/api/presentation/2/context.json",
			"motivation": "sc:painting",
			"@type": "oa:Annotation",
			"@id": "https://kraus1933.acdh.oeaw.ac.at/iiif_manifests/HIN-176044/HIN-176044_0289/transkript.json#line_1561558435870_724",
			"on": "https://kraus1933.acdh.oeaw.ac.at/iiif_manifests/HIN-176044/HIN-176044_0289#xywh=241,1331,308,94"
		},
		{
			"resource": {
				"format": "text/plain",
				"language": "de",
				"@type": "cnt:ContentAsText",
				"chars": "[??]"
			},
			"@context": "https://iiif.io/api/presentation/2/context.json",
			"motivation": "sc:painting",
			"@type": "oa:Annotation",
			"@id": "https://kraus1933.acdh.oeaw.ac.at/iiif_manifests/HIN-176044/HIN-176044_0289/transkript.json#line_1561558441129_727",
			"on": "https://kraus1933.acdh.oeaw.ac.at/iiif_manifests/HIN-176044/HIN-176044_0289#xywh=299,1396,219,104"
		},
		{
			"resource": {
				"format": "text/plain",
				"language": "de",
				"@type": "cnt:ContentAsText",
				"chars": "[??]"
			},
			"@context": "https://iiif.io/api/presentation/2/context.json",
			"motivation": "sc:painting",
			"@type": "oa:Annotation",
			"@id": "https://kraus1933.acdh.oeaw.ac.at/iiif_manifests/HIN-176044/HIN-176044_0289/transkript.json#line_1561558447911_730",
			"on": "https://kraus1933.acdh.oeaw.ac.at/iiif_manifests/HIN-176044/HIN-176044_0289#xywh=262,1453,265,113"
		}
	],
	"@context": "https://iiif.io/api/presentation/2/context.json",
	"@type": "sc:AnnotationList",
	"@id": "https://kraus1933.acdh.oeaw.ac.at/iiif_manifests/HIN-176044/HIN-176044_0289/transkript.json"
}