{
	"resources": [
		{
			"resource": {
				"format": "text/plain",
				"language": "de",
				"@type": "cnt:ContentAsText",
				"chars": "Mitleid mit d[?] Kranken[?]"
			},
			"@context": "https://iiif.io/api/presentation/2/context.json",
			"motivation": "sc:painting",
			"@type": "oa:Annotation",
			"@id": "https://kraus1933.acdh.oeaw.ac.at/iiif_manifests/HIN-177198/HIN-177198_0076/transkript.json#line_1563475057858_2649",
			"on": "https://kraus1933.acdh.oeaw.ac.at/iiif_manifests/HIN-177198/HIN-177198_0076#xywh=1085,1242,719,171"
		},
		{
			"resource": {
				"format": "text/plain",
				"language": "de",
				"@type": "cnt:ContentAsText",
				"chars": "[??]"
			},
			"@context": "https://iiif.io/api/presentation/2/context.json",
			"motivation": "sc:painting",
			"@type": "oa:Annotation",
			"@id": "https://kraus1933.acdh.oeaw.ac.at/iiif_manifests/HIN-177198/HIN-177198_0076/transkript.json#line_1563475060862_2652",
			"on": "https://kraus1933.acdh.oeaw.ac.at/iiif_manifests/HIN-177198/HIN-177198_0076#xywh=1110,1419,549,189"
		},
		{
			"resource": {
				"format": "text/plain",
				"language": "de",
				"@type": "cnt:ContentAsText",
				"chars": "[??]Hitler"
			},
			"@context": "https://iiif.io/api/presentation/2/context.json",
			"motivation": "sc:painting",
			"@type": "oa:Annotation",
			"@id": "https://kraus1933.acdh.oeaw.ac.at/iiif_manifests/HIN-177198/HIN-177198_0076/transkript.json#line_1563475065596_2655",
			"on": "https://kraus1933.acdh.oeaw.ac.at/iiif_manifests/HIN-177198/HIN-177198_0076#xywh=1115,1548,562,158"
		},
		{
			"resource": {
				"format": "text/plain",
				"language": "de",
				"@type": "cnt:ContentAsText",
				"chars": "Nichts zu F\u00fchrer"
			},
			"@context": "https://iiif.io/api/presentation/2/context.json",
			"motivation": "sc:painting",
			"@type": "oa:Annotation",
			"@id": "https://kraus1933.acdh.oeaw.ac.at/iiif_manifests/HIN-177198/HIN-177198_0076/transkript.json#line_1563475070048_2658",
			"on": "https://kraus1933.acdh.oeaw.ac.at/iiif_manifests/HIN-177198/HIN-177198_0076#xywh=1167,1608,492,152"
		}
	],
	"@context": "https://iiif.io/api/presentation/2/context.json",
	"@type": "sc:AnnotationList",
	"@id": "https://kraus1933.acdh.oeaw.ac.at/iiif_manifests/HIN-177198/HIN-177198_0076/transkript.json"
}