{
	"resources": [
		{
			"resource": {
				"format": "text/plain",
				"language": "de",
				"@type": "cnt:ContentAsText",
				"chars": "[??] Volkes[?]"
			},
			"@context": "https://iiif.io/api/presentation/2/context.json",
			"motivation": "sc:painting",
			"@type": "oa:Annotation",
			"@id": "https://kraus1933.acdh.oeaw.ac.at/iiif_manifests/HIN-177198/HIN-177198_0122/transkript.json#line_1563442576305_563",
			"on": "https://kraus1933.acdh.oeaw.ac.at/iiif_manifests/HIN-177198/HIN-177198_0122#xywh=1024,991,1141,243"
		},
		{
			"resource": {
				"format": "text/plain",
				"language": "de",
				"@type": "cnt:ContentAsText",
				"chars": "dieser[?] Trottel[?], da\u00df[?]"
			},
			"@context": "https://iiif.io/api/presentation/2/context.json",
			"motivation": "sc:painting",
			"@type": "oa:Annotation",
			"@id": "https://kraus1933.acdh.oeaw.ac.at/iiif_manifests/HIN-177198/HIN-177198_0122/transkript.json#line_1563442578343_566",
			"on": "https://kraus1933.acdh.oeaw.ac.at/iiif_manifests/HIN-177198/HIN-177198_0122#xywh=978,1234,609,148"
		},
		{
			"resource": {
				"format": "text/plain",
				"language": "de",
				"@type": "cnt:ContentAsText",
				"chars": "\u201eAuf letzter Stufe h\u00f6ren auf die Dinge\u201c"
			},
			"@context": "https://iiif.io/api/presentation/2/context.json",
			"motivation": "sc:painting",
			"@type": "oa:Annotation",
			"@id": "https://kraus1933.acdh.oeaw.ac.at/iiif_manifests/HIN-177198/HIN-177198_0122/transkript.json#line_1563442582533_569",
			"on": "https://kraus1933.acdh.oeaw.ac.at/iiif_manifests/HIN-177198/HIN-177198_0122#xywh=1046,1414,1274,204"
		},
		{
			"resource": {
				"format": "text/plain",
				"language": "de",
				"@type": "cnt:ContentAsText",
				"chars": "moralischer Beifall[?]"
			},
			"@context": "https://iiif.io/api/presentation/2/context.json",
			"motivation": "sc:painting",
			"@type": "oa:Annotation",
			"@id": "https://kraus1933.acdh.oeaw.ac.at/iiif_manifests/HIN-177198/HIN-177198_0122/transkript.json#line_1563442585615_572",
			"on": "https://kraus1933.acdh.oeaw.ac.at/iiif_manifests/HIN-177198/HIN-177198_0122#xywh=1399,1654,566,124"
		},
		{
			"resource": {
				"format": "text/plain",
				"language": "de",
				"@type": "cnt:ContentAsText",
				"chars": "Stolz auf \u00d6sterreich"
			},
			"@context": "https://iiif.io/api/presentation/2/context.json",
			"motivation": "sc:painting",
			"@type": "oa:Annotation",
			"@id": "https://kraus1933.acdh.oeaw.ac.at/iiif_manifests/HIN-177198/HIN-177198_0122/transkript.json#line_1563442615838_587",
			"on": "https://kraus1933.acdh.oeaw.ac.at/iiif_manifests/HIN-177198/HIN-177198_0122#xywh=1797,1724,488,156"
		},
		{
			"resource": {
				"format": "text/plain",
				"language": "de",
				"@type": "cnt:ContentAsText",
				"chars": "Es einmal[?] [?]"
			},
			"@context": "https://iiif.io/api/presentation/2/context.json",
			"motivation": "sc:painting",
			"@type": "oa:Annotation",
			"@id": "https://kraus1933.acdh.oeaw.ac.at/iiif_manifests/HIN-177198/HIN-177198_0122/transkript.json#line_1563442587383_575",
			"on": "https://kraus1933.acdh.oeaw.ac.at/iiif_manifests/HIN-177198/HIN-177198_0122#xywh=906,1761,445,77"
		},
		{
			"resource": {
				"format": "text/plain",
				"language": "de",
				"@type": "cnt:ContentAsText",
				"chars": "einen Tagschreiber[?] der so viel"
			},
			"@context": "https://iiif.io/api/presentation/2/context.json",
			"motivation": "sc:painting",
			"@type": "oa:Annotation",
			"@id": "https://kraus1933.acdh.oeaw.ac.at/iiif_manifests/HIN-177198/HIN-177198_0122/transkript.json#line_1563442603681_578",
			"on": "https://kraus1933.acdh.oeaw.ac.at/iiif_manifests/HIN-177198/HIN-177198_0122#xywh=870,1773,964,196"
		},
		{
			"resource": {
				"format": "text/plain",
				"language": "de",
				"@type": "cnt:ContentAsText",
				"chars": "Geist hat, da\u00df er [?] aus[?] [?]"
			},
			"@context": "https://iiif.io/api/presentation/2/context.json",
			"motivation": "sc:painting",
			"@type": "oa:Annotation",
			"@id": "https://kraus1933.acdh.oeaw.ac.at/iiif_manifests/HIN-177198/HIN-177198_0122/transkript.json#line_1563442608596_581",
			"on": "https://kraus1933.acdh.oeaw.ac.at/iiif_manifests/HIN-177198/HIN-177198_0122#xywh=923,1872,707,158"
		},
		{
			"resource": {
				"format": "text/plain",
				"language": "de",
				"@type": "cnt:ContentAsText",
				"chars": "\u00dcberf\u00fclle[?] zu [??]"
			},
			"@context": "https://iiif.io/api/presentation/2/context.json",
			"motivation": "sc:painting",
			"@type": "oa:Annotation",
			"@id": "https://kraus1933.acdh.oeaw.ac.at/iiif_manifests/HIN-177198/HIN-177198_0122/transkript.json#line_1563442613285_584",
			"on": "https://kraus1933.acdh.oeaw.ac.at/iiif_manifests/HIN-177198/HIN-177198_0122#xywh=1011,1940,643,136"
		},
		{
			"resource": {
				"format": "text/plain",
				"language": "de",
				"@type": "cnt:ContentAsText",
				"chars": "[??]"
			},
			"@context": "https://iiif.io/api/presentation/2/context.json",
			"motivation": "sc:painting",
			"@type": "oa:Annotation",
			"@id": "https://kraus1933.acdh.oeaw.ac.at/iiif_manifests/HIN-177198/HIN-177198_0122/transkript.json#line_1563442621525_590",
			"on": "https://kraus1933.acdh.oeaw.ac.at/iiif_manifests/HIN-177198/HIN-177198_0122#xywh=1016,2103,1082,255"
		},
		{
			"resource": {
				"format": "text/plain",
				"language": "de",
				"@type": "cnt:ContentAsText",
				"chars": "Wegen gesetz Fall"
			},
			"@context": "https://iiif.io/api/presentation/2/context.json",
			"motivation": "sc:painting",
			"@type": "oa:Annotation",
			"@id": "https://kraus1933.acdh.oeaw.ac.at/iiif_manifests/HIN-177198/HIN-177198_0122/transkript.json#line_1563442628107_593",
			"on": "https://kraus1933.acdh.oeaw.ac.at/iiif_manifests/HIN-177198/HIN-177198_0122#xywh=1137,2263,862,179"
		},
		{
			"resource": {
				"format": "text/plain",
				"language": "de",
				"@type": "cnt:ContentAsText",
				"chars": "[??]"
			},
			"@context": "https://iiif.io/api/presentation/2/context.json",
			"motivation": "sc:painting",
			"@type": "oa:Annotation",
			"@id": "https://kraus1933.acdh.oeaw.ac.at/iiif_manifests/HIN-177198/HIN-177198_0122/transkript.json#line_1563442632020_596",
			"on": "https://kraus1933.acdh.oeaw.ac.at/iiif_manifests/HIN-177198/HIN-177198_0122#xywh=1103,2331,745,216"
		},
		{
			"resource": {
				"format": "text/plain",
				"language": "de",
				"@type": "cnt:ContentAsText",
				"chars": "[??]"
			},
			"@context": "https://iiif.io/api/presentation/2/context.json",
			"motivation": "sc:painting",
			"@type": "oa:Annotation",
			"@id": "https://kraus1933.acdh.oeaw.ac.at/iiif_manifests/HIN-177198/HIN-177198_0122/transkript.json#line_1563442638002_599",
			"on": "https://kraus1933.acdh.oeaw.ac.at/iiif_manifests/HIN-177198/HIN-177198_0122#xywh=1103,2428,939,211"
		},
		{
			"resource": {
				"format": "text/plain",
				"language": "de",
				"@type": "cnt:ContentAsText",
				"chars": "[?]"
			},
			"@context": "https://iiif.io/api/presentation/2/context.json",
			"motivation": "sc:painting",
			"@type": "oa:Annotation",
			"@id": "https://kraus1933.acdh.oeaw.ac.at/iiif_manifests/HIN-177198/HIN-177198_0122/transkript.json#line_1563442640952_602",
			"on": "https://kraus1933.acdh.oeaw.ac.at/iiif_manifests/HIN-177198/HIN-177198_0122#xywh=1316,2608,396,94"
		},
		{
			"resource": {
				"format": "text/plain",
				"language": "de",
				"@type": "cnt:ContentAsText",
				"chars": "[??]"
			},
			"@context": "https://iiif.io/api/presentation/2/context.json",
			"motivation": "sc:painting",
			"@type": "oa:Annotation",
			"@id": "https://kraus1933.acdh.oeaw.ac.at/iiif_manifests/HIN-177198/HIN-177198_0122/transkript.json#line_1563442646490_605",
			"on": "https://kraus1933.acdh.oeaw.ac.at/iiif_manifests/HIN-177198/HIN-177198_0122#xywh=1146,2474,1197,352"
		},
		{
			"resource": {
				"format": "text/plain",
				"language": "de",
				"@type": "cnt:ContentAsText",
				"chars": "12. II."
			},
			"@context": "https://iiif.io/api/presentation/2/context.json",
			"motivation": "sc:painting",
			"@type": "oa:Annotation",
			"@id": "https://kraus1933.acdh.oeaw.ac.at/iiif_manifests/HIN-177198/HIN-177198_0122/transkript.json#line_1563442650255_608",
			"on": "https://kraus1933.acdh.oeaw.ac.at/iiif_manifests/HIN-177198/HIN-177198_0122#xywh=909,2890,243,141"
		},
		{
			"resource": {
				"format": "text/plain",
				"language": "de",
				"@type": "cnt:ContentAsText",
				"chars": "[??]"
			},
			"@context": "https://iiif.io/api/presentation/2/context.json",
			"motivation": "sc:painting",
			"@type": "oa:Annotation",
			"@id": "https://kraus1933.acdh.oeaw.ac.at/iiif_manifests/HIN-177198/HIN-177198_0122/transkript.json#line_1563442654765_611",
			"on": "https://kraus1933.acdh.oeaw.ac.at/iiif_manifests/HIN-177198/HIN-177198_0122#xywh=1052,2768,1260,284"
		},
		{
			"resource": {
				"format": "text/plain",
				"language": "de",
				"@type": "cnt:ContentAsText",
				"chars": "Weltrevolution"
			},
			"@context": "https://iiif.io/api/presentation/2/context.json",
			"motivation": "sc:painting",
			"@type": "oa:Annotation",
			"@id": "https://kraus1933.acdh.oeaw.ac.at/iiif_manifests/HIN-177198/HIN-177198_0122/transkript.json#line_1563442658881_614",
			"on": "https://kraus1933.acdh.oeaw.ac.at/iiif_manifests/HIN-177198/HIN-177198_0122#xywh=1084,3021,624,129"
		},
		{
			"resource": {
				"format": "text/plain",
				"language": "de",
				"@type": "cnt:ContentAsText",
				"chars": "[??]"
			},
			"@context": "https://iiif.io/api/presentation/2/context.json",
			"motivation": "sc:painting",
			"@type": "oa:Annotation",
			"@id": "https://kraus1933.acdh.oeaw.ac.at/iiif_manifests/HIN-177198/HIN-177198_0122/transkript.json#line_1563442672112_632",
			"on": "https://kraus1933.acdh.oeaw.ac.at/iiif_manifests/HIN-177198/HIN-177198_0122#xywh=967,3125,1064,299"
		},
		{
			"resource": {
				"format": "text/plain",
				"language": "de",
				"@type": "cnt:ContentAsText",
				"chars": "[??]"
			},
			"@context": "https://iiif.io/api/presentation/2/context.json",
			"motivation": "sc:painting",
			"@type": "oa:Annotation",
			"@id": "https://kraus1933.acdh.oeaw.ac.at/iiif_manifests/HIN-177198/HIN-177198_0122/transkript.json#line_1563442675821_635",
			"on": "https://kraus1933.acdh.oeaw.ac.at/iiif_manifests/HIN-177198/HIN-177198_0122#xywh=1098,3220,831,218"
		},
		{
			"resource": {
				"format": "text/plain",
				"language": "de",
				"@type": "cnt:ContentAsText",
				"chars": "[??]"
			},
			"@context": "https://iiif.io/api/presentation/2/context.json",
			"motivation": "sc:painting",
			"@type": "oa:Annotation",
			"@id": "https://kraus1933.acdh.oeaw.ac.at/iiif_manifests/HIN-177198/HIN-177198_0122/transkript.json#line_1563442681805_638",
			"on": "https://kraus1933.acdh.oeaw.ac.at/iiif_manifests/HIN-177198/HIN-177198_0122#xywh=1129,3339,801,151"
		},
		{
			"resource": {
				"format": "text/plain",
				"language": "de",
				"@type": "cnt:ContentAsText",
				"chars": "[??]"
			},
			"@context": "https://iiif.io/api/presentation/2/context.json",
			"motivation": "sc:painting",
			"@type": "oa:Annotation",
			"@id": "https://kraus1933.acdh.oeaw.ac.at/iiif_manifests/HIN-177198/HIN-177198_0122/transkript.json#line_1563442688440_641",
			"on": "https://kraus1933.acdh.oeaw.ac.at/iiif_manifests/HIN-177198/HIN-177198_0122#xywh=1226,3378,782,182"
		},
		{
			"resource": {
				"format": "text/plain",
				"language": "de",
				"@type": "cnt:ContentAsText",
				"chars": "Die gr\u00f6\u00dfte"
			},
			"@context": "https://iiif.io/api/presentation/2/context.json",
			"motivation": "sc:painting",
			"@type": "oa:Annotation",
			"@id": "https://kraus1933.acdh.oeaw.ac.at/iiif_manifests/HIN-177198/HIN-177198_0122/transkript.json#line_1563442660993_617",
			"on": "https://kraus1933.acdh.oeaw.ac.at/iiif_manifests/HIN-177198/HIN-177198_0122#xywh=2050,2919,350,150"
		},
		{
			"resource": {
				"format": "text/plain",
				"language": "de",
				"@type": "cnt:ContentAsText",
				"chars": "L\u00fcge"
			},
			"@context": "https://iiif.io/api/presentation/2/context.json",
			"motivation": "sc:painting",
			"@type": "oa:Annotation",
			"@id": "https://kraus1933.acdh.oeaw.ac.at/iiif_manifests/HIN-177198/HIN-177198_0122/transkript.json#line_1563442662876_620",
			"on": "https://kraus1933.acdh.oeaw.ac.at/iiif_manifests/HIN-177198/HIN-177198_0122#xywh=2053,3038,301,102"
		},
		{
			"resource": {
				"format": "text/plain",
				"language": "de",
				"@type": "cnt:ContentAsText",
				"chars": "Sentimental"
			},
			"@context": "https://iiif.io/api/presentation/2/context.json",
			"motivation": "sc:painting",
			"@type": "oa:Annotation",
			"@id": "https://kraus1933.acdh.oeaw.ac.at/iiif_manifests/HIN-177198/HIN-177198_0122/transkript.json#line_1563442664466_623",
			"on": "https://kraus1933.acdh.oeaw.ac.at/iiif_manifests/HIN-177198/HIN-177198_0122#xywh=2062,3128,406,128"
		},
		{
			"resource": {
				"format": "text/plain",
				"language": "de",
				"@type": "cnt:ContentAsText",
				"chars": "[?]"
			},
			"@context": "https://iiif.io/api/presentation/2/context.json",
			"motivation": "sc:painting",
			"@type": "oa:Annotation",
			"@id": "https://kraus1933.acdh.oeaw.ac.at/iiif_manifests/HIN-177198/HIN-177198_0122/transkript.json#line_1563442666111_626",
			"on": "https://kraus1933.acdh.oeaw.ac.at/iiif_manifests/HIN-177198/HIN-177198_0122#xywh=2079,3218,262,104"
		},
		{
			"resource": {
				"format": "text/plain",
				"language": "de",
				"@type": "cnt:ContentAsText",
				"chars": "[?]"
			},
			"@context": "https://iiif.io/api/presentation/2/context.json",
			"motivation": "sc:painting",
			"@type": "oa:Annotation",
			"@id": "https://kraus1933.acdh.oeaw.ac.at/iiif_manifests/HIN-177198/HIN-177198_0122/transkript.json#line_1563442667791_629",
			"on": "https://kraus1933.acdh.oeaw.ac.at/iiif_manifests/HIN-177198/HIN-177198_0122#xywh=2077,3293,206,124"
		},
		{
			"resource": {
				"format": "text/plain",
				"language": "de",
				"@type": "cnt:ContentAsText",
				"chars": "Sollen es Keinem dank, da\u00df kein Pogrom."
			},
			"@context": "https://iiif.io/api/presentation/2/context.json",
			"motivation": "sc:painting",
			"@type": "oa:Annotation",
			"@id": "https://kraus1933.acdh.oeaw.ac.at/iiif_manifests/HIN-177198/HIN-177198_0122/transkript.json#line_1563442692329_644",
			"on": "https://kraus1933.acdh.oeaw.ac.at/iiif_manifests/HIN-177198/HIN-177198_0122#xywh=981,3517,1236,230"
		},
		{
			"resource": {
				"format": "text/plain",
				"language": "de",
				"@type": "cnt:ContentAsText",
				"chars": "Warum mir das gef\u00e4llt? 2 [?] 2 Rest"
			},
			"@context": "https://iiif.io/api/presentation/2/context.json",
			"motivation": "sc:painting",
			"@type": "oa:Annotation",
			"@id": "https://kraus1933.acdh.oeaw.ac.at/iiif_manifests/HIN-177198/HIN-177198_0122/transkript.json#line_1563442697114_647",
			"on": "https://kraus1933.acdh.oeaw.ac.at/iiif_manifests/HIN-177198/HIN-177198_0122#xywh=1054,3619,1204,189"
		},
		{
			"resource": {
				"format": "text/plain",
				"language": "de",
				"@type": "cnt:ContentAsText",
				"chars": "sprengen[?]"
			},
			"@context": "https://iiif.io/api/presentation/2/context.json",
			"motivation": "sc:painting",
			"@type": "oa:Annotation",
			"@id": "https://kraus1933.acdh.oeaw.ac.at/iiif_manifests/HIN-177198/HIN-177198_0122/transkript.json#line_1563442698697_650",
			"on": "https://kraus1933.acdh.oeaw.ac.at/iiif_manifests/HIN-177198/HIN-177198_0122#xywh=1933,3725,250,122"
		}
	],
	"@context": "https://iiif.io/api/presentation/2/context.json",
	"@type": "sc:AnnotationList",
	"@id": "https://kraus1933.acdh.oeaw.ac.at/iiif_manifests/HIN-177198/HIN-177198_0122/transkript.json"
}