{
	"resources": [
		{
			"resource": {
				"format": "text/plain",
				"language": "de",
				"@type": "cnt:ContentAsText",
				"chars": "103 [von fremder Hand]"
			},
			"@context": "https://iiif.io/api/presentation/2/context.json",
			"motivation": "sc:painting",
			"@type": "oa:Annotation",
			"@id": "https://kraus1933.ace.oeaw.ac.at/resources/json/HIN-176044/HIN-176044_0205/transkript.json#line_1561565727749_1105",
			"on": "https://kraus1933.ace.oeaw.ac.at/resources/json/HIN-176044/HIN-176044_0205#xywh=822,141,139,100"
		},
		{
			"resource": {
				"format": "text/plain",
				"language": "de",
				"@type": "cnt:ContentAsText",
				"chars": "Zehntausende deutsche"
			},
			"@context": "https://iiif.io/api/presentation/2/context.json",
			"motivation": "sc:painting",
			"@type": "oa:Annotation",
			"@id": "https://kraus1933.ace.oeaw.ac.at/resources/json/HIN-176044/HIN-176044_0205/transkript.json#line_1561565734329_1108",
			"on": "https://kraus1933.ace.oeaw.ac.at/resources/json/HIN-176044/HIN-176044_0205#xywh=176,309,513,209"
		},
		{
			"resource": {
				"format": "text/plain",
				"language": "de",
				"@type": "cnt:ContentAsText",
				"chars": "Arbeiter schmachten"
			},
			"@context": "https://iiif.io/api/presentation/2/context.json",
			"motivation": "sc:painting",
			"@type": "oa:Annotation",
			"@id": "https://kraus1933.ace.oeaw.ac.at/resources/json/HIN-176044/HIN-176044_0205/transkript.json#line_1561565742293_1111",
			"on": "https://kraus1933.ace.oeaw.ac.at/resources/json/HIN-176044/HIN-176044_0205#xywh=266,461,526,122"
		},
		{
			"resource": {
				"format": "text/plain",
				"language": "de",
				"@type": "cnt:ContentAsText",
				"chars": "in Gef\u00e4ngnissen und"
			},
			"@context": "https://iiif.io/api/presentation/2/context.json",
			"motivation": "sc:painting",
			"@type": "oa:Annotation",
			"@id": "https://kraus1933.ace.oeaw.ac.at/resources/json/HIN-176044/HIN-176044_0205/transkript.json#line_1561565748500_1114",
			"on": "https://kraus1933.ace.oeaw.ac.at/resources/json/HIN-176044/HIN-176044_0205#xywh=244,564,450,130"
		},
		{
			"resource": {
				"format": "text/plain",
				"language": "de",
				"@type": "cnt:ContentAsText",
				"chars": "Konzentrationslagern."
			},
			"@context": "https://iiif.io/api/presentation/2/context.json",
			"motivation": "sc:painting",
			"@type": "oa:Annotation",
			"@id": "https://kraus1933.ace.oeaw.ac.at/resources/json/HIN-176044/HIN-176044_0205/transkript.json#line_1561565752711_1117",
			"on": "https://kraus1933.ace.oeaw.ac.at/resources/json/HIN-176044/HIN-176044_0205#xywh=241,675,445,120"
		},
		{
			"resource": {
				"format": "text/plain",
				"language": "de",
				"@type": "cnt:ContentAsText",
				"chars": "\u201eer lehne es ab, [?]"
			},
			"@context": "https://iiif.io/api/presentation/2/context.json",
			"motivation": "sc:painting",
			"@type": "oa:Annotation",
			"@id": "https://kraus1933.ace.oeaw.ac.at/resources/json/HIN-176044/HIN-176044_0205/transkript.json#line_1561565760324_1120",
			"on": "https://kraus1933.ace.oeaw.ac.at/resources/json/HIN-176044/HIN-176044_0205#xywh=184,795,679,155"
		},
		{
			"resource": {
				"format": "text/plain",
				"language": "de",
				"@type": "cnt:ContentAsText",
				"chars": "[??]"
			},
			"@context": "https://iiif.io/api/presentation/2/context.json",
			"motivation": "sc:painting",
			"@type": "oa:Annotation",
			"@id": "https://kraus1933.ace.oeaw.ac.at/resources/json/HIN-176044/HIN-176044_0205/transkript.json#line_1561565765888_1123",
			"on": "https://kraus1933.ace.oeaw.ac.at/resources/json/HIN-176044/HIN-176044_0205#xywh=219,909,280,136"
		},
		{
			"resource": {
				"format": "text/plain",
				"language": "de",
				"@type": "cnt:ContentAsText",
				"chars": "auf das niedrige"
			},
			"@context": "https://iiif.io/api/presentation/2/context.json",
			"motivation": "sc:painting",
			"@type": "oa:Annotation",
			"@id": "https://kraus1933.ace.oeaw.ac.at/resources/json/HIN-176044/HIN-176044_0205/transkript.json#line_1561565775619_1126",
			"on": "https://kraus1933.ace.oeaw.ac.at/resources/json/HIN-176044/HIN-176044_0205#xywh=344,941,416,142"
		},
		{
			"resource": {
				"format": "text/plain",
				"language": "de",
				"@type": "cnt:ContentAsText",
				"chars": "Niveau Jouhaux"
			},
			"@context": "https://iiif.io/api/presentation/2/context.json",
			"motivation": "sc:painting",
			"@type": "oa:Annotation",
			"@id": "https://kraus1933.ace.oeaw.ac.at/resources/json/HIN-176044/HIN-176044_0205/transkript.json#line_1561565785056_1129",
			"on": "https://kraus1933.ace.oeaw.ac.at/resources/json/HIN-176044/HIN-176044_0205#xywh=211,1037,630,138"
		},
		{
			"resource": {
				"format": "text/plain",
				"language": "de",
				"@type": "cnt:ContentAsText",
				"chars": "herabzusteigen."
			},
			"@context": "https://iiif.io/api/presentation/2/context.json",
			"motivation": "sc:painting",
			"@type": "oa:Annotation",
			"@id": "https://kraus1933.ace.oeaw.ac.at/resources/json/HIN-176044/HIN-176044_0205/transkript.json#line_1561565792146_1132",
			"on": "https://kraus1933.ace.oeaw.ac.at/resources/json/HIN-176044/HIN-176044_0205#xywh=217,1161,480,117"
		},
		{
			"resource": {
				"format": "text/plain",
				"language": "de",
				"@type": "cnt:ContentAsText",
				"chars": "Wenn er sich als"
			},
			"@context": "https://iiif.io/api/presentation/2/context.json",
			"motivation": "sc:painting",
			"@type": "oa:Annotation",
			"@id": "https://kraus1933.ace.oeaw.ac.at/resources/json/HIN-176044/HIN-176044_0205/transkript.json#line_1561565798272_1135",
			"on": "https://kraus1933.ace.oeaw.ac.at/resources/json/HIN-176044/HIN-176044_0205#xywh=287,1235,421,103"
		},
		{
			"resource": {
				"format": "text/plain",
				"language": "de",
				"@type": "cnt:ContentAsText",
				"chars": "Anwalt von Verbrechern"
			},
			"@context": "https://iiif.io/api/presentation/2/context.json",
			"motivation": "sc:painting",
			"@type": "oa:Annotation",
			"@id": "https://kraus1933.ace.oeaw.ac.at/resources/json/HIN-176044/HIN-176044_0205/transkript.json#line_1561565804559_1138",
			"on": "https://kraus1933.ace.oeaw.ac.at/resources/json/HIN-176044/HIN-176044_0205#xywh=241,1313,551,136"
		},
		{
			"resource": {
				"format": "text/plain",
				"language": "de",
				"@type": "cnt:ContentAsText",
				"chars": "aufspiele, so sei"
			},
			"@context": "https://iiif.io/api/presentation/2/context.json",
			"motivation": "sc:painting",
			"@type": "oa:Annotation",
			"@id": "https://kraus1933.ace.oeaw.ac.at/resources/json/HIN-176044/HIN-176044_0205/transkript.json#line_1561565810678_1141",
			"on": "https://kraus1933.ace.oeaw.ac.at/resources/json/HIN-176044/HIN-176044_0205#xywh=304,1392,461,114"
		},
		{
			"resource": {
				"format": "text/plain",
				"language": "de",
				"@type": "cnt:ContentAsText",
				"chars": "das seine Sache."
			},
			"@context": "https://iiif.io/api/presentation/2/context.json",
			"motivation": "sc:painting",
			"@type": "oa:Annotation",
			"@id": "https://kraus1933.ace.oeaw.ac.at/resources/json/HIN-176044/HIN-176044_0205/transkript.json#line_1561565816474_1144",
			"on": "https://kraus1933.ace.oeaw.ac.at/resources/json/HIN-176044/HIN-176044_0205#xywh=328,1476,434,112"
		},
		{
			"resource": {
				"format": "text/plain",
				"language": "de",
				"@type": "cnt:ContentAsText",
				"chars": "Man kennt Deutschland"
			},
			"@context": "https://iiif.io/api/presentation/2/context.json",
			"motivation": "sc:painting",
			"@type": "oa:Annotation",
			"@id": "https://kraus1933.ace.oeaw.ac.at/resources/json/HIN-176044/HIN-176044_0205/transkript.json#line_1561565822699_1147",
			"on": "https://kraus1933.ace.oeaw.ac.at/resources/json/HIN-176044/HIN-176044_0205#xywh=222,1574,584,130"
		},
		{
			"resource": {
				"format": "text/plain",
				"language": "de",
				"@type": "cnt:ContentAsText",
				"chars": "nicht. So lade"
			},
			"@context": "https://iiif.io/api/presentation/2/context.json",
			"motivation": "sc:painting",
			"@type": "oa:Annotation",
			"@id": "https://kraus1933.ace.oeaw.ac.at/resources/json/HIN-176044/HIN-176044_0205/transkript.json#line_1561565828339_1150",
			"on": "https://kraus1933.ace.oeaw.ac.at/resources/json/HIN-176044/HIN-176044_0205#xywh=339,1680,404,146"
		}
	],
	"@context": "https://iiif.io/api/presentation/2/context.json",
	"@type": "sc:AnnotationList",
	"@id": "https://kraus1933.ace.oeaw.ac.at/resources/json/HIN-176044/HIN-176044_0205/transkript.json"
}