{
	"resources": [
		{
			"resource": {
				"format": "text/plain",
				"language": "de",
				"@type": "cnt:ContentAsText",
				"chars": "Indiskutabel"
			},
			"@context": "https://iiif.io/api/presentation/2/context.json",
			"motivation": "sc:painting",
			"@type": "oa:Annotation",
			"@id": "https://kraus1933.ace.oeaw.ac.at/resources/json/HIN-177198/HIN-177198_0160/transkript.json#line_1563439953964_687",
			"on": "https://kraus1933.ace.oeaw.ac.at/resources/json/HIN-177198/HIN-177198_0160#xywh=945,1039,951,246"
		},
		{
			"resource": {
				"format": "text/plain",
				"language": "de",
				"@type": "cnt:ContentAsText",
				"chars": "[?]"
			},
			"@context": "https://iiif.io/api/presentation/2/context.json",
			"motivation": "sc:painting",
			"@type": "oa:Annotation",
			"@id": "https://kraus1933.ace.oeaw.ac.at/resources/json/HIN-177198/HIN-177198_0160/transkript.json#line_1563439956374_690",
			"on": "https://kraus1933.ace.oeaw.ac.at/resources/json/HIN-177198/HIN-177198_0160#xywh=1222,1260,624,182"
		},
		{
			"resource": {
				"format": "text/plain",
				"language": "de",
				"@type": "cnt:ContentAsText",
				"chars": "Reichspost!"
			},
			"@context": "https://iiif.io/api/presentation/2/context.json",
			"motivation": "sc:painting",
			"@type": "oa:Annotation",
			"@id": "https://kraus1933.ace.oeaw.ac.at/resources/json/HIN-177198/HIN-177198_0160/transkript.json#line_1563439959312_693",
			"on": "https://kraus1933.ace.oeaw.ac.at/resources/json/HIN-177198/HIN-177198_0160#xywh=888,1512,800,290"
		},
		{
			"resource": {
				"format": "text/plain",
				"language": "de",
				"@type": "cnt:ContentAsText",
				"chars": "Wer bei Namen"
			},
			"@context": "https://iiif.io/api/presentation/2/context.json",
			"motivation": "sc:painting",
			"@type": "oa:Annotation",
			"@id": "https://kraus1933.ace.oeaw.ac.at/resources/json/HIN-177198/HIN-177198_0160/transkript.json#line_1563439963360_696",
			"on": "https://kraus1933.ace.oeaw.ac.at/resources/json/HIN-177198/HIN-177198_0160#xywh=888,1833,851,240"
		},
		{
			"resource": {
				"format": "text/plain",
				"language": "de",
				"@type": "cnt:ContentAsText",
				"chars": "Dollfu\u00df nicht aufschreckte[?]"
			},
			"@context": "https://iiif.io/api/presentation/2/context.json",
			"motivation": "sc:painting",
			"@type": "oa:Annotation",
			"@id": "https://kraus1933.ace.oeaw.ac.at/resources/json/HIN-177198/HIN-177198_0160/transkript.json#line_1563439966858_699",
			"on": "https://kraus1933.ace.oeaw.ac.at/resources/json/HIN-177198/HIN-177198_0160#xywh=957,2003,1147,252"
		},
		{
			"resource": {
				"format": "text/plain",
				"language": "de",
				"@type": "cnt:ContentAsText",
				"chars": "\u201eVorsprung\u201c"
			},
			"@context": "https://iiif.io/api/presentation/2/context.json",
			"motivation": "sc:painting",
			"@type": "oa:Annotation",
			"@id": "https://kraus1933.ace.oeaw.ac.at/resources/json/HIN-177198/HIN-177198_0160/transkript.json#line_1563439969864_702",
			"on": "https://kraus1933.ace.oeaw.ac.at/resources/json/HIN-177198/HIN-177198_0160#xywh=888,2255,523,328"
		}
	],
	"@context": "https://iiif.io/api/presentation/2/context.json",
	"@type": "sc:AnnotationList",
	"@id": "https://kraus1933.ace.oeaw.ac.at/resources/json/HIN-177198/HIN-177198_0160/transkript.json"
}